{
  "open_top_drawer": [
    {
      "id": 26,
      "corner": [
        [
          271,
          406
        ],
        [
          243,
          402
        ],
        [
          241,
          369
        ],
        [
          267,
          372
        ]
      ]
    },
    {
      "id": 27,
      "corner": [
        [
          250,
          67
        ],
        [
          255,
          106
        ],
        [
          229,
          111
        ],
        [
          222,
          73
        ]
      ]
    }
  ]
}