[
    {
        "num_marker_seen": 0,
        "stage2_retry": null,
        "pixel_error": null,
        "proj_func": null
    },
    {
        "num_marker_seen": 0,
        "stage2_retry": null,
        "pixel_error": null,
        "proj_func": null
    },
    {
        "num_marker_seen": 55,
        "stage2_retry": 1,
        "pixel_error": 1.2480555525871668,
        "proj_func": "hand_marker_proj_world_camera",
        "camera_base_ori": [
            [
                0.6594626670357626,
                0.06872902063011001,
                0.7485888808346713
            ],
            [
                -0.021719338492296774,
                -0.9936540849996711,
                0.11036226573843995
            ],
            [
                0.7514234898654266,
                -0.08903864939839867,
                -0.6537850241415532
            ]
        ],
        "camera_base_ori_rotvec": [
            -2.760877736053356,
            -0.03924760805664978,
            -1.252335581269731
        ],
        "camera_base_pos": [
            -0.6286935754553445,
            -0.5774871392226245,
            0.3136381080778968
        ],
        "p_marker_ee": [
            0.02046848092881245,
            0.07635835497903606,
            0.067782954853385
        ]
    }
]